rionid/__init__.py
rionid/__main__.py
rionid/baseline.py
rionid/core.py
rionid/external/__init__.py
rionid/external/barion/__init__.py
rionid/external/barion/amedata.py
rionid/external/barion/particle.py
rionid/external/barion/ring.py
rionid/external/lisereader/__init__.py
rionid/external/lisereader/reader.py
rionid/gui/__init__.py
rionid/gui/app.py
rionid/gui/controller.py
rionid/gui/dialogs.py
rionid/gui/inputs.py
rionid/gui/plot.py
rionid/io.py
rionid/version.py
rionid-8.0.0.dist-info/LICENSE
rionid-8.0.0.dist-info/METADATA
rionid-8.0.0.dist-info/WHEEL
rionid-8.0.0.dist-info/entry_points.txt
rionid-8.0.0.dist-info/RECORD
