Metadata-Version: 2.1
Name: rionid
Version: 8.0.0
Summary: Ring-stored ion IDentification: A pure Python tool for Schottky spectrum analysis.
Home-page: https://gsi-nuclear-astrophysics.github.io/rionid/
License: GPL-3.0-or-later
Keywords: Physics,Nuclear Physics,Storage Rings,Mass Spectrometry,Schottky
Author: David Freire-Fernández
Author-email: D.FreireFernandez@gsi.de
Requires-Python: >=3.9,<3.13
Classifier: Development Status :: 5 - Production/Stable
Classifier: Intended Audience :: Science/Research
Classifier: License :: OSI Approved :: GNU General Public License v3 or later (GPLv3+)
Classifier: Programming Language :: Python :: 3
Classifier: Programming Language :: Python :: 3.9
Classifier: Programming Language :: Python :: 3.10
Classifier: Programming Language :: Python :: 3.11
Classifier: Programming Language :: Python :: 3.12
Classifier: Topic :: Scientific/Engineering :: Physics
Requires-Dist: PyQt5 (>=5.15.9,<6.0.0)
Requires-Dist: ezodf (>=0.3.2,<0.4.0)
Requires-Dist: fortranformat (>=2.0.3,<3.0.0)
Requires-Dist: loguru (>=0.7.0,<0.8.0)
Requires-Dist: lxml (>=4.9.3,<5.0.0)
Requires-Dist: numpy (>=2.0.2,<3.0.0)
Requires-Dist: pyqtgraph (>=0.13.3,<0.14.0)
Requires-Dist: requests (>=2.31.0,<3.0.0)
Requires-Dist: scipy (>=1.10.1,<2.0.0)
Requires-Dist: toml (>=0.10.2,<0.11.0)
Project-URL: Bug Tracker, https://github.com/GSI-Nuclear-Astrophysics/rionid/issues
Project-URL: Documentation, https://gsi-nuclear-astrophysics.github.io/rionid/
Project-URL: Repository, https://github.com/GSI-Nuclear-Astrophysics/rionid
Project-URL: Source Code, https://github.com/GSI-Nuclear-Astrophysics/rionid
